{
  "tournament_name": "Unnamed Tournament 010",
  "format": "Pauper",
  "date": "Unknown Date",
  "top_8": [
    {
      "rank": 1,
      "decklist": "https://www.moxfield.com/decks/kykt88uJxEePRowoPaIESQ"
    },
    {
      "rank": 2,
      "decklist": "https://www.moxfield.com/decks/tyy5ehPb3Ea-A-e0ISdC2Q"
    },
    {
      "rank": 3,
      "decklist": "https://www.moxfield.com/decks/1xUq86O2I0mo3slLwTHBpg"
    },
    {
      "rank": 4,
      "decklist": "https://www.moxfield.com/decks/_r2XaxwVS0GZt_yaQAxvag"
    },
    {
      "rank": 5,
      "decklist": "https://www.moxfield.com/decks/BYGi0hvetkaiNsHJK95u2w"
    },
    {
      "rank": 6,
      "decklist": "https://www.moxfield.com/decks/xEo9sWhAUEuaUr01UWBMTw"
    },
    {
      "rank": 7,
      "decklist": "https://www.moxfield.com/decks/vNzXCjyb40O4JuKKn9ctuQ"
    },
    {
      "rank": 8,
      "decklist": "https://www.moxfield.com/decks/Cq6bawp-X0CD_yFEWLAyOw"
    }
  ]
}