{
  "tournament_name": "Unnamed Tournament 019",
  "format": "7pt Highlander",
  "date": "Unknown Date",
  "top_8": [
    {
      "rank": 1,
      "decklist": "https://moxfield.com/decks/rk9LfwU_c0qFVEv7eIo23Q"
    },
    {
      "rank": 2,
      "decklist": "https://moxfield.com/decks/f949Pe49I0G8ky6cSsm5Rw"
    },
    {
      "rank": 3,
      "decklist": "https://moxfield.com/decks/ZPELJ3ye1kOCP1GxdLLPjA"
    },
    {
      "rank": 4,
      "decklist": "https://moxfield.com/decks/tAgKr83C1EuecW4HPYbzNQ"
    },
    {
      "rank": 5,
      "decklist": "https://moxfield.com/decks/T246vfpum0SxhhX6K3s0uw"
    },
    {
      "rank": 6,
      "decklist": "https://moxfield.com/decks/UGPRsy17tEqFuA6uqpjB_Q"
    },
    {
      "rank": 7,
      "decklist": "https://moxfield.com/decks/Valzn7fjM0SLN_xRdryBwA"
    },
    {
      "rank": 8,
      "decklist": "https://moxfield.com/decks/NcOA3XCezkeBcBrABOlTxw"
    }
  ]
}