{
  "tournament_name": "Unnamed Tournament 037",
  "format": "Legacy",
  "date": "Unknown Date",
  "top_8": [
    {
      "rank": 1,
      "decklist": "https://moxfield.com/decks/NZFxY1FggkivlYBeGcHSmw"
    },
    {
      "rank": 2,
      "decklist": "https://moxfield.com/decks/GOjwwdaMaku26AGYgAAYjA"
    },
    {
      "rank": 3,
      "decklist": "https://moxfield.com/decks/DR3ZaOF2S0SZoaDRLJOedg"
    },
    {
      "rank": 4,
      "decklist": "https://moxfield.com/decks/oXRI0MUbB0WKMPT8_Ctg5w"
    },
    {
      "rank": 5,
      "decklist": "No decklist available"
    },
    {
      "rank": 6,
      "decklist": "https://moxfield.com/decks/Nn038XwqPkWx4yHqkkzBbg"
    },
    {
      "rank": 7,
      "decklist": "https://moxfield.com/decks/YQERsT_TdUiJuX7pORkrnA"
    },
    {
      "rank": 8,
      "decklist": "https://moxfield.com/decks/C_NHomBVUkGIzbLYUpreAw"
    }
  ]
}